qtorch_posit/__init__.py
qtorch_posit/number.py
qtorch_posit/posit_activation.py
qtorch_posit/auto_low/__init__.py
qtorch_posit/auto_low/auto_low.py
qtorch_posit/optim/__init__.py
qtorch_posit/optim/optim_low.py
qtorch_posit/quant/__init__.py
qtorch_posit/quant/quant_function.py
qtorch_posit/quant/quant_module.py
qtorch_posit/quant/quant_cpu/bit_helper.cpp
qtorch_posit/quant/quant_cpu/quant_cpu.cpp
qtorch_posit/quant/quant_cpu/quant_cpu.h
qtorch_posit/quant/quant_cpu/sim_helper.cpp
qtorch_posit/quant/quant_cuda/._float_kernel.cu
qtorch_posit/quant/quant_cuda/._posit_kernel.cu
qtorch_posit/quant/quant_cuda/._quant.cu
qtorch_posit/quant/quant_cuda/._quant_cuda.h
qtorch_posit/quant/quant_cuda/._quant_kernel.h
qtorch_posit/quant/quant_cuda/bit_helper.cu
qtorch_posit/quant/quant_cuda/block_kernel.cu
qtorch_posit/quant/quant_cuda/fixed_point_kernel.cu
qtorch_posit/quant/quant_cuda/float_kernel.cu
qtorch_posit/quant/quant_cuda/posit_kernel.cu
qtorch_posit/quant/quant_cuda/quant.cu
qtorch_posit/quant/quant_cuda/quant_cuda.cpp
qtorch_posit/quant/quant_cuda/quant_cuda.h
qtorch_posit/quant/quant_cuda/quant_kernel.h
qtorch_posit/quant/quant_cuda/sim_helper.cu
qtorch_posit-0.2.0.dist-info/LICENSE
qtorch_posit-0.2.0.dist-info/METADATA
qtorch_posit-0.2.0.dist-info/WHEEL
qtorch_posit-0.2.0.dist-info/top_level.txt
qtorch_posit-0.2.0.dist-info/RECORD
