Metadata-Version: 2.1
Name: qtorch-posit
Version: 0.2.0
Summary: Low-Precision Arithmetic Simulation in Pytorch - Extension for Posit
Home-page: UNKNOWN
Author: Extension: Minh Ho, Himeshi, Original: Tianyi Zhang, Zhiqiu Lin, Guandao Yang, Christopher De Sa,
Author-email: minhhn@comp.nus.edu.sg
License: MIT
Project-URL: Documentation, https://qpytorch.readthedocs.io
Project-URL: Source, https://github.com/minhhn2910/QPyTorch
Platform: UNKNOWN
Requires-Python: >=3.6
Requires-Dist: torch (>=1.5.0)
